["\"{\\\"ref_id\\\":\\\"400486\\\",\\\"userId\\\":\\\"1176986\\\",\\\"id\\\":\\\"400486\\\",\\\"title\\\":\\\"1188 Bidwell\\\",\\\"price\\\":\\\"2138 - 4700\\\",\\\"type\\\":\\\"Apartment\\\",\\\"sq_feet\\\":\\\"500, 600, 660, 730, 1080\\\",\\\"availability\\\":\\\"Immediate\\\",\\\"avdate\\\":\\\"Immediate\\\",\\\"location\\\":\\\"West End\\\",\\\"rented\\\":\\\"Not-Rented\\\",\\\"thumb\\\":\\\"https:\\\\/\\\\/f1a3d4fea3a9a877e732-356deb4d9644d2835b7712e712dbd1ea.ssl.cf2.rackcdn.com\\\\/400486\\\\/thumber_5793259.v.00e74caed587d10ab1175ab7596dfeaa.jpg\\\",\\\"thumb2\\\":\\\"https:\\\\/\\\\/f1a3d4fea3a9a877e732-356deb4d9644d2835b7712e712dbd1ea.ssl.cf2.rackcdn.com\\\\/400486\\\\/thumber_5793259.v.00e74caed587d10ab1175ab7596dfeaa.jpg\\\",\\\"slide\\\":\\\"https:\\\\/\\\\/f1a3d4fea3a9a877e732-356deb4d9644d2835b7712e712dbd1ea.ssl.cf2.rackcdn.com\\\\/400486\\\\/slide_5793259.v.00e74caed587d10ab1175ab7596dfeaa.jpg\\\",\\\"link\\\":\\\"\\\\/bc\\\\/vancouver\\\\/rentals\\\\/apartment\\\\/1-bedroom\\\\/west-end\\\\/pet-friendly\\\\/400486\\\",\\\"latitude\\\":\\\"49.286393600000\\\",\\\"longitude\\\":\\\"-123.139899500000\\\",\\\"marker\\\":\\\"2a56ad4c97377c6a7db7f5ebe310f05c\\\",\\\"address\\\":\\\"1188 Bidwell Street\\\",\\\"address_hidden\\\":false,\\\"city\\\":\\\"Vancouver\\\",\\\"province\\\":\\\"British Columbia\\\",\\\"intro\\\":\\\"1188 Bidwell Street\\\",\\\"community\\\":\\\"West End\\\",\\\"quadrant\\\":null,\\\"phone\\\":\\\"778-875-9200\\\",\\\"phone_2\\\":\\\"\\\",\\\"preferred_contact\\\":\\\"Phone||Text||Email\\\",\\\"website\\\":\\\"http:\\\\/\\\\/1188bidwell.com\\\\/\\\",\\\"email\\\":1,\\\"smoking\\\":\\\"Non-Smoking\\\",\\\"lease_term\\\":\\\"Long Term\\\",\\\"garage_size\\\":\\\"underground\\\",\\\"status\\\":\\\"active\\\",\\\"bedrooms\\\":\\\"1 - bachelor\\\",\\\"den\\\":\\\"No, Yes\\\",\\\"baths\\\":\\\"1 - 2\\\",\\\"cats\\\":true,\\\"dogs\\\":true,\\\"utilities_included\\\":false}\""]
